odoo/addons/pos_discount_all/README.rst
odoo/addons/pos_discount_all/__init__.py
odoo/addons/pos_discount_all/__manifest__.py
odoo/addons/pos_discount_all/demo/product_product.xml
odoo/addons/pos_discount_all/demo/res_groups.xml
odoo/addons/pos_discount_all/i18n/es.po
odoo/addons/pos_discount_all/i18n/fr.po
odoo/addons/pos_discount_all/i18n/it.po
odoo/addons/pos_discount_all/i18n/pos_discount_all.pot
odoo/addons/pos_discount_all/models/__init__.py
odoo/addons/pos_discount_all/models/pos_session.py
odoo/addons/pos_discount_all/models/product_template.py
odoo/addons/pos_discount_all/readme/CONFIGURE.rst
odoo/addons/pos_discount_all/readme/CONTRIBUTORS.rst
odoo/addons/pos_discount_all/readme/CREDITS.rst
odoo/addons/pos_discount_all/readme/DESCRIPTION.rst
odoo/addons/pos_discount_all/readme/DEVELOP.rst
odoo/addons/pos_discount_all/readme/USAGE.rst
odoo/addons/pos_discount_all/static/description/icon.png
odoo/addons/pos_discount_all/static/description/index.html
odoo/addons/pos_discount_all/static/description/order_summary.png
odoo/addons/pos_discount_all/static/description/pos_receipt.png
odoo/addons/pos_discount_all/static/description/product_template_form.png
odoo/addons/pos_discount_all/static/src/js/models.js
odoo/addons/pos_discount_all/static/src/xml/OrderSummary.xml
odoo/addons/pos_discount_all/tests/__init__.py
odoo/addons/pos_discount_all/tests/test_module.py
odoo/addons/pos_discount_all/tests/tours/PosDiscountAllTour.tour.js
odoo/addons/pos_discount_all/views/view_product_template.xml
odoo_addon_pos_discount_all-16.0.1.0.1.8.dist-info/METADATA
odoo_addon_pos_discount_all-16.0.1.0.1.8.dist-info/WHEEL
odoo_addon_pos_discount_all-16.0.1.0.1.8.dist-info/top_level.txt
odoo_addon_pos_discount_all-16.0.1.0.1.8.dist-info/RECORD
